{
  "id": "frag_eco_GEO_gcc_latest_039",
  "domain": "economy",
  "subdomain": "GEO",
  "sector": "GEO",
  "tags": [
    "gcc",
    "vision_2030",
    "latest_data"
  ],
  "reasoning_role": "latest_data",
  "content": "GCC developments 2024: Saudi Vision 2030 accelerating (NEOM, PIF $700B+ AUM). UAE diversification advanced (non-oil 70% GDP). Qatar post-blockade relations normalized. Oman pursuing neutral diplomacy. GCC-India FTA negotiations ongoing. Climate commitments (UAE COP28, Saudi Green Initiative). Regional tensions (Iran, Yemen) affecting investment climate.",
  "source": "gcc_statistical_center",
  "source_url": "https://www.gccstat.org/",
  "credibility_class": "international_organization",
  "year": 2024,
  "weight": 0.91
}