{
  "id": "frag_fin_rsi_indicator_counter_argument_01",
  "domain": "finance",
  "subdomain": "technical_analysis",
  "tags": [
    "technical_analysis",
    "rsi",
    "oversold",
    "overbought",
    "divergence",
    "counter_argument",
    "rsi_indicator"
  ],
  "reasoning_role": "counter_argument",
  "content": "RSI's overbought/oversold thresholds are arbitrary and vary by asset. Strong trends can keep RSI overbought/oversold for extended periods, generating premature reversal signals. Backtests show RSI alone has minimal predictive value. Divergence signals are subjective and often only clear in hindsight. Wilder's original parameters (14-period) lack theoretical justification. RSI performs no better than random in efficient markets. Multiple testing across parameters leads to data mining bias.",
  "source": "Educational Resource",
  "source_url": "https://www.nytimes.com/markets/rsi-limitations-study",
  "credibility_class": "educational_resource",
  "year": 2024,
  "compatible_with": [],
  "incompatible_with": [],
  "weight": 1.0
}