{
  "id": "frag_eco_GEO_container_shipping_latest_014",
  "domain": "economy",
  "tags": [
    "container_shipping",
    "logistics",
    "rate_volatility",
    "latest_data"
  ],
  "content": "Container shipping 2024: Red Sea attacks forcing Cape rerouting, adding 10-14 days transit time. Rates up 150-200% on Asia-Europe routes. Panama Canal drought restrictions easing. New vessel deliveries creating overcapacity concerns. Port strikes avoided at US East Coast. Digitalization (bill of lading) progressing slowly.",
  "source": "lloyds_list",
  "source_url": "https://lloydslist.maritimeintelligence.informa.com/",
  "credibility_class": "industry_publication",
  "last_verified": "2026-05-12",
  "weight": 0.91,
  "compatible_with": [],
  "incompatible_with": [],
  "subdomain": "GEO",
  "sector": "GEO",
  "reasoning_role": "latest_data",
  "source_type": null,
  "year": 2024,
  "sub_question": null,
  "verified": null,
  "_original_credibility_class": null,
  "_reasoning_role_auto_classified": null,
  "grundy_value": -1,
  "robustness_status": "PENDING"
}