{
  "id": "frag_eco_GEO_dollar_dominance_counter_026",
  "domain": "economy",
  "subdomain": "GEO",
  "sector": "GEO",
  "tags": [
    "dollar",
    "reserve_currency",
    "challenges",
    "counter_argument"
  ],
  "reasoning_role": "counter_argument",
  "content": "Dollar vulnerability factors: US fiscal deficits unsustainable long-term ($34T debt, 7%+ deficit). Political polarization risks debt ceiling crises. Sanctions weaponization creating incentives for alternatives. Rising US-China decoupling fragments system. Digital currencies could bypass traditional channels. However, no near-term replacement viable.",
  "source": "cfr_dollar_analysis",
  "source_url": "https://www.cfr.org/",
  "credibility_class": "think_tank",
  "year": 2024,
  "weight": 0.89
}