{
  "id": "REG-023",
  "domain": "economy",
  "subdomain": "REG",
  "tags": [
    "fsoc",
    "sifi",
    "systemic_risk",
    "non_bank",
    "financial_stability"
  ],
  "reasoning_role": "definition",
  "content": "FSOC (Financial Stability Oversight Council) systemic risk designation process identifies non-bank SIFIs. Process: (1) Three-stage analytical framework\u2014Stage 1 (quantitative screening), Stage 2 (Committee evaluation), Stage 3 (Council vote), (2) Evaluation criteria\u2014size, interconnectedness, substitutability, leverage, liquidity risk, (3) Designation triggers enhanced prudential standards (Fed supervision, stress testing, capital/liquidity requirements), (4) Due process\u2014notice, hearing opportunity, written basis. History: 4 designations 2013-2014 (AIG, GE Capital, Prudential, MetLife); MetLife designation vacated by court 2016; GE Capital/AIG de-designated 2017; Prudential 2018. 2019 guidance shifted to activities-based approach vs. entity-based. 2023 final rule restored entity-based approach, added climate risk consideration. Current focus: asset managers, private credit, insurers, payment processors, crypto intermediaries.",
  "source": "regulatory_source",
  "source_url": "https://www.bis.org",
  "credibility_class": "international_institution",
  "year": 2024,
  "compatible_with": [],
  "incompatible_with": [],
  "weight": 1.0,
  "sector": "REG"
}