{
  "id": "frag_ph_cancer_prevention_at_population_level_definition_0097",
  "domain": "healthcare",
  "subdomain": "PH",
  "sector": "PH",
  "tags": [
    "cancer",
    "prevention",
    "screening",
    "vaccination"
  ],
  "reasoning_role": "definition",
  "content": "Cancer prevention encompasses primary prevention (reducing incidence by addressing risk factors), secondary prevention (early detection through screening), and tertiary prevention (reducing complications in diagnosed patients). An estimated 30-50% of cancers are preventable. Major modifiable risk factors include: tobacco use (22% of cancer deaths), alcohol consumption, obesity/overweight, physical inactivity, unhealthy diet, occupational carcinogens, environmental pollutants, and infections (HPV, HBV, HCV, H. pylori causing 13% of cancers globally). Primary prevention strategies target these factors through policy and individual interventions. Vaccination against HPV (cervical, anal, oropharyngeal cancers) and HBV (liver cancer) represents highly effective primary prevention. Secondary prevention through evidence-based screening reduces mortality from breast, cervical, colorectal, and lung cancers.",
  "source": "CDC",
  "source_url": "https://www.cdc.gov",
  "credibility_class": "A",
  "year": 2024,
  "compatible_with": [],
  "incompatible_with": [],
  "weight": 1.0
}