{
  "id": "frag_gov_ipl_pat_application_process_procedural_005",
  "domain": "governance",
  "sector": "IPL",
  "subdomain": "GOV",
  "reasoning_role": "definition",
  "credibility_class": "government_source",
  "year": 2024,
  "weight": 1.0,
  "grundy_value": -1,
  "robustness_status": "PENDING",
  "source_url": "https://www.un.org",
  "tags": [
    "GOV",
    "definition"
  ],
  "content": "Fragment frag_gov_ipl_pat_application_process_procedural_005",
  "source": "Unknown",
  "credibility_score": "UNVERIFIED",
  "source_domain": "www.un.org"
}