{
  "id": "MED-2072_nephrology_glomerular_definition",
  "domain": "science_technology",
  "subdomain": "BIO",
  "sector": "BIO",
  "tags": [
    "nephrology glomerular",
    "clinical_medicine",
    "definition"
  ],
  "reasoning_role": "definition",
  "content": "Nephrology Glomerular - pathophysiology, diagnostic criteria, clinical presentation",
  "source_url": "https://pubmed.ncbi.nlm.nih.gov",
  "credibility_class": "peer_reviewed",
  "year": 2026,
  "source": "PubMed",
  "original_domain": "healthcare",
  "original_sector": "MED"
}